dlpx/__init__.py
dlpx/virtualization/__init__.py
dlpx/virtualization/common/__init__.py
dlpx/virtualization/common/_common_classes.py
dlpx/virtualization/common/exceptions.py
appdata_workflow_test_libs-1.0.0.dist-info/LICENSE
appdata_workflow_test_libs-1.0.0.dist-info/METADATA
appdata_workflow_test_libs-1.0.0.dist-info/WHEEL
appdata_workflow_test_libs-1.0.0.dist-info/top_level.txt
appdata_workflow_test_libs-1.0.0.dist-info/RECORD
