Metadata-Version: 2.1
Name: appdata-workflow-test-libs
Version: 1.0.0
Summary: UNKNOWN
Home-page: https://developer.delphix.com
Author: Sourabh
Author-email: sourabh@delphix.com
License: UNKNOWN
Platform: UNKNOWN
Classifier: Development Status :: 5 - Production/Stable
Classifier: Programming Language :: Python
Classifier: Programming Language :: Python :: 2.7
Classifier: Programming Language :: Python :: 3.8
Classifier: License :: OSI Approved :: Apache Software License
Classifier: Operating System :: OS Independent
Requires-Python: >=2.7, <3.9, !=3.0.*, !=3.1.*, !=3.2.*, !=3.3.*, !=3.4.*, !=3.5.*, !=3.6.*, !=3.7.*
